serializers/__init__.py
serializers/factory.py
serializers/json_serializer/JsonSerializer.py
serializers/json_serializer/__init__.py
serializers/json_serializer/serialization_logic.py
serializers/src/__init__.py
serializers/src/constants.py
serializers/src/deserialization.py
serializers/src/serialization.py
serializers/xml_serializer/XmlSerializer.py
serializers/xml_serializer/__init__.py
serializers/xml_serializer/serialization_logic.py
igi_lab3-1.0.dist-info/METADATA
igi_lab3-1.0.dist-info/WHEEL
igi_lab3-1.0.dist-info/top_level.txt
igi_lab3-1.0.dist-info/RECORD
